CompyledFunc/__init__.py
CompyledFunc-0.1.8.dist-info/DESCRIPTION.rst
CompyledFunc-0.1.8.dist-info/METADATA
CompyledFunc-0.1.8.dist-info/metadata.json
CompyledFunc-0.1.8.dist-info/RECORD
CompyledFunc-0.1.8.dist-info/top_level.txt
CompyledFunc-0.1.8.dist-info/WHEEL
