Metadata-Version: 2.0
Name: CompyledFunc
Version: 0.1.8
Summary: Compiled functions via Sympy/Theano
Home-page: https://github.com/MBALearnsToCode/CompyledFunc
Author: Vinh Luong (a.k.a. MBALearnsToCode)
Author-email: MBALearnsToCode@UChicago.edu
License: MIT License
Keywords: sympy theano compile
Platform: UNKNOWN
Requires-Dist: HelpyFuncs
Requires-Dist: NumPy
Requires-Dist: SymPy
Requires-Dist: Theano
